EventService/__init__.py
EventService/__main__.py
EventService/api.py
EventService/const.py
EventService/service.py
pih_event-1.31.dist-info/METADATA
pih_event-1.31.dist-info/WHEEL
pih_event-1.31.dist-info/entry_points.txt
pih_event-1.31.dist-info/top_level.txt
pih_event-1.31.dist-info/RECORD
