Metadata-Version: 2.1
Name: pih-event
Version: 1.31
Summary: PIH Log and Event service package
Home-page: https://pacifichosp.com/
Author: Nikita Karachentsev
Author-email: it@pacifichosp.com
License: MIT
Requires-Dist: ipih
Requires-Dist: telegram-send
